spyder_modelx/__init__.py
spyder_modelx/_version.py
spyder_modelx/kernelspec/__init__.py
spyder_modelx/kernelspec/mxkernelspec_5.py
spyder_modelx/kernelspec/mxkernelspec_6.py
spyder_modelx/plugins/__init__.py
spyder_modelx/plugins/analyzer_plugin.py
spyder_modelx/plugins/analyzer_plugin_5.py
spyder_modelx/plugins/analyzer_plugin_6.py
spyder_modelx/plugins/dataview_plugin.py
spyder_modelx/plugins/dataview_plugin_5.py
spyder_modelx/plugins/dataview_plugin_6.py
spyder_modelx/plugins/mxconsole_5_3.py
spyder_modelx/plugins/mxconsole_6_0.py
spyder_modelx/plugins/mxplugin.py
spyder_modelx/plugins/mxplugin_4.py
spyder_modelx/plugins/mxplugin_5.py
spyder_modelx/plugins/mxplugin_5_2.py
spyder_modelx/plugins/mxplugin_5_3.py
spyder_modelx/plugins/mxplugin_5_base.py
spyder_modelx/plugins/mxplugin_6_0.py
spyder_modelx/plugins/shellconnect.py
spyder_modelx/plugins/stacked_mixin.py
spyder_modelx/tests/__init__.py
spyder_modelx/tests/test_plugin.py
spyder_modelx/tests/fromspyder/__init__.py
spyder_modelx/tests/fromspyder/test_mxdataview.py
spyder_modelx/utility/__init__.py
spyder_modelx/utility/formula.py
spyder_modelx/utility/tupleencoder.py
spyder_modelx/utility/typeutil.py
spyder_modelx/widgets/__init__.py
spyder_modelx/widgets/mxclient.py
spyder_modelx/widgets/mxcodelist.py
spyder_modelx/widgets/mxdatalist.py
spyder_modelx/widgets/mxlineedit.py
spyder_modelx/widgets/mxproperty.py
spyder_modelx/widgets/mxtoolbar.py
spyder_modelx/widgets/mxtreemodel.py
spyder_modelx/widgets/mxanalyzer/__init__.py
spyder_modelx/widgets/mxanalyzer/mxanalyzer_5.py
spyder_modelx/widgets/mxanalyzer/mxanalyzer_6.py
spyder_modelx/widgets/mxcodeeditor/__init__.py
spyder_modelx/widgets/mxcodeeditor/mxcodeeditor_5.py
spyder_modelx/widgets/mxcodeeditor/mxcodeeditor_6.py
spyder_modelx/widgets/mxdataviewer/__init__.py
spyder_modelx/widgets/mxdataviewer/compat32/__init__.py
spyder_modelx/widgets/mxdataviewer/compat32/arrayviewer.py
spyder_modelx/widgets/mxdataviewer/compat32/collectionsviewer.py
spyder_modelx-0.15.0.dist-info/licenses/LICENSE.GPL.txt
spyder_modelx-0.15.0.dist-info/licenses/LICENSE.txt
spyder_modelx-0.15.0.dist-info/METADATA
spyder_modelx-0.15.0.dist-info/WHEEL
spyder_modelx-0.15.0.dist-info/entry_points.txt
spyder_modelx-0.15.0.dist-info/top_level.txt
spyder_modelx-0.15.0.dist-info/RECORD
